numbalsoda/__init__.py
numbalsoda/driver.py
numbalsoda/driver_dop853.py
numbalsoda/driver_solve_ivp.py
numbalsoda/libdop853.dll
numbalsoda/libdop853.dll.a
numbalsoda/liblsoda.dll
numbalsoda/liblsoda.dll.a
numbalsoda/libsolve_ivp.dll
numbalsoda/libsolve_ivp.dll.a
numbalsoda-0.3.4.dist-info/LICENSE.txt
numbalsoda-0.3.4.dist-info/METADATA
numbalsoda-0.3.4.dist-info/WHEEL
numbalsoda-0.3.4.dist-info/top_level.txt
numbalsoda-0.3.4.dist-info/RECORD
