Metadata-Version: 2.1
Name: numbalsoda
Version: 0.3.4
Summary: Python wrapper of LSODA (solving ODEs) which can be called from within numba functions.
Home-page: https://github.com/Nicholaswogan/numbalsoda
Author: Nicholas Wogan
Author-email: nicholaswogan@gmail.com
License: MIT
Platform: UNKNOWN
Requires-Python: >3.6
License-File: LICENSE.txt
Requires-Dist: numpy
Requires-Dist: numba
